pytgcalls/__init__.py
pytgcalls/__version__.py
pytgcalls/binding.py
pytgcalls/environment.py
pytgcalls/exceptions.py
pytgcalls/ffprobe.py
pytgcalls/file_manager.py
pytgcalls/pytgcalls.py
pytgcalls/pytgcalls_session.py
pytgcalls/scaffold.py
pytgcalls/stream_type.py
pytgcalls/sync.py
pytgcalls/version_manager.py
pytgcalls/custom_api/__init__.py
pytgcalls/custom_api/custom_api.py
pytgcalls/dist/binding.js
pytgcalls/dist/buffer_optimized.js
pytgcalls/dist/ffmpeg_reader.js
pytgcalls/dist/file_reader.js
pytgcalls/dist/index.js
pytgcalls/dist/rtc-connection.js
pytgcalls/dist/sdp-builder.js
pytgcalls/dist/stream.js
pytgcalls/dist/tgcalls.js
pytgcalls/dist/types.js
pytgcalls/dist/utils.js
pytgcalls/handlers/__init__.py
pytgcalls/handlers/handlers_holder.py
pytgcalls/media_devices/__init__.py
pytgcalls/media_devices/device_info.py
pytgcalls/media_devices/media_devices.py
pytgcalls/media_devices/screen_info.py
pytgcalls/methods/__init__.py
pytgcalls/methods/core/__init__.py
pytgcalls/methods/core/binding_runner.py
pytgcalls/methods/core/join_voice_call.py
pytgcalls/methods/core/leave_voice_call.py
pytgcalls/methods/core/set_video_call_status.py
pytgcalls/methods/decorators/__init__.py
pytgcalls/methods/decorators/on_closed_voice_chat.py
pytgcalls/methods/decorators/on_group_call_invite.py
pytgcalls/methods/decorators/on_kicked.py
pytgcalls/methods/decorators/on_left.py
pytgcalls/methods/decorators/on_participants_change.py
pytgcalls/methods/decorators/on_raw_update.py
pytgcalls/methods/decorators/on_stream_end.py
pytgcalls/methods/groups/__init__.py
pytgcalls/methods/groups/active_calls.py
pytgcalls/methods/groups/calls.py
pytgcalls/methods/groups/change_volume_call.py
pytgcalls/methods/groups/get_active_call.py
pytgcalls/methods/groups/get_call.py
pytgcalls/methods/groups/get_participants.py
pytgcalls/methods/groups/join_group_call.py
pytgcalls/methods/groups/leave_group_call.py
pytgcalls/methods/handlers/__init__.py
pytgcalls/methods/handlers/raw_update_handler.py
py_tgcalls_kaizoku-0.9.5.dist-info/LICENSE
py_tgcalls_kaizoku-0.9.5.dist-info/METADATA
py_tgcalls_kaizoku-0.9.5.dist-info/WHEEL
py_tgcalls_kaizoku-0.9.5.dist-info/top_level.txt
py_tgcalls_kaizoku-0.9.5.dist-info/RECORD
